flicker_utils.cp38-win_amd64.pyd
python_example.cp38-win_amd64.pyd
flicker_utils-0.0.1.dist-info/LICENSE
flicker_utils-0.0.1.dist-info/METADATA
flicker_utils-0.0.1.dist-info/WHEEL
flicker_utils-0.0.1.dist-info/top_level.txt
flicker_utils-0.0.1.dist-info/RECORD
