Metadata-Version: 2.1
Name: flicker-utils
Version: 0.0.1
Summary: A test project using pybind11
Home-page: https://github.com/pybind/python_example
Author: Sylvain Corlay
Author-email: sylvain.corlay@gmail.com
Requires-Python: >=3.7
License-File: LICENSE
Provides-Extra: test
Requires-Dist: pytest ; extra == 'test'
